README.rst
setup.py
NotificationOptOutPlugin.egg-info/PKG-INFO
NotificationOptOutPlugin.egg-info/SOURCES.txt
NotificationOptOutPlugin.egg-info/dependency_links.txt
NotificationOptOutPlugin.egg-info/entry_points.txt
NotificationOptOutPlugin.egg-info/not-zip-safe
NotificationOptOutPlugin.egg-info/top_level.txt
notificationoptout/__init__.py
notificationoptout/api.py