Metadata-Version: 1.0
Name: NotificationOptOutPlugin
Version: 0.1.2
Summary: Allow users to opt-out from notifications.
Home-page: http://mitar.tnode.com/
Author: Mitar
Author-email: mitar.trac@tnode.com
License: AGPLv3
Keywords: trac plugin
Platform: UNKNOWN
